{
  "analytics_identifier": null,
  "base_path": "/cma-cases/email-signup",
  "content_id": "43dd2b13-93ec-4ca6-a7a4-e2eb5f5d485a",
  "document_type": "finder_email_signup",
  "first_published_at": "2015-08-17T13:28:37.000+00:00",
  "locale": "en",
  "phase": "live",
  "public_updated_at": "2019-12-30T11:14:06.000+00:00",
  "publishing_app": "specialist-publisher",
  "publishing_scheduled_at": null,
  "rendering_app": "finder-frontend",
  "scheduled_publishing_delay_seconds": null,
  "schema_name": "finder_email_signup",
  "title": "Competition and Markets Authority cases",
  "updated_at": "2019-12-30T11:21:05.768Z",
  "withdrawn_notice": {},
  "publishing_request_id": "24198-1577704672.422-10.13.3.248-531",
  "links": {
    "organisations": [
      {
        "content_id": "957eb4ec-089b-4f71-ba2a-dc69ac8919ea",
        "title": "Competition and Markets Authority",
        "locale": "en",
        "analytics_identifier": "D550",
        "api_path": "/api/content/government/organisations/competition-and-markets-authority",
        "base_path": "/government/organisations/competition-and-markets-authority",
        "document_type": "organisation",
        "schema_name": "organisation",
        "withdrawn": false,
        "details": {
          "logo": {
            "formatted_title": "Competition and <br/>Markets Authority",
            "image": {
              "url": "https://assets.publishing.service.gov.uk/government/uploads/system/uploads/organisation/logo/550/CMA_Logo_01.png",
              "alt_text": "Competition and Markets Authority"
            }
          },
          "brand": "department-for-business-innovation-skills",
          "default_news_image": null
        },
        "links": {},
        "api_url": "https://www.gov.uk/api/content/government/organisations/competition-and-markets-authority",
        "web_url": "https://www.gov.uk/government/organisations/competition-and-markets-authority"
      }
    ],
    "related": [
      {
        "content_id": "fef4ac7c-024a-4943-9f19-e85a8369a1f3",
        "title": "Competition and Markets Authority cases",
        "locale": "en",
        "api_path": "/api/content/cma-cases",
        "base_path": "/cma-cases",
        "document_type": "finder",
        "public_updated_at": "2019-12-30T11:14:06Z",
        "schema_name": "finder",
        "withdrawn": false,
        "links": {},
        "api_url": "https://www.gov.uk/api/content/cma-cases",
        "web_url": "https://www.gov.uk/cma-cases"
      }
    ],
    "available_translations": [
      {
        "title": "Competition and Markets Authority cases",
        "public_updated_at": "2019-12-30T11:14:06Z",
        "document_type": "finder_email_signup",
        "schema_name": "finder_email_signup",
        "base_path": "/cma-cases/email-signup",
        "api_path": "/api/content/cma-cases/email-signup",
        "withdrawn": false,
        "content_id": "43dd2b13-93ec-4ca6-a7a4-e2eb5f5d485a",
        "locale": "en",
        "api_url": "https://www.gov.uk/api/content/cma-cases/email-signup",
        "web_url": "https://www.gov.uk/cma-cases/email-signup",
        "links": {}
      }
    ]
  },
  "description": "You'll get an email each time a case is updated or a new case is published.",
  "details": {
    "beta": false,
    "email_filter_facets": [
      {
        "facet_id": "case_type",
        "facet_name": "Case type",
        "facet_choices": [
          {
            "key": "ca98-and-civil-cartels",
            "radio_button_name": "CA98 and civil cartels",
            "topic_name": "CA98 and civil cartels",
            "prechecked": false
          },
          {
            "key": "competition-disqualification",
            "radio_button_name": "Competition disqualification",
            "topic_name": "competition disqualification",
            "prechecked": false
          },
          {
            "key": "criminal-cartels",
            "radio_button_name": "Criminal cartels",
            "topic_name": "criminal cartels",
            "prechecked": false
          },
          {
            "key": "markets",
            "radio_button_name": "Markets",
            "topic_name": "markets",
            "prechecked": false
          },
          {
            "key": "mergers",
            "radio_button_name": "Mergers",
            "topic_name": "mergers",
            "prechecked": false
          },
          {
            "key": "consumer-enforcement",
            "radio_button_name": "Consumer enforcement",
            "topic_name": "consumer enforcement",
            "prechecked": false
          },
          {
            "key": "regulatory-references-and-appeals",
            "radio_button_name": "Regulatory references and appeals",
            "topic_name": "regulatory references and appeals",
            "prechecked": false
          },
          {
            "key": "review-of-orders-and-undertakings",
            "radio_button_name": "Reviews of orders and undertakings",
            "topic_name": "reviews of orders and undertakings",
            "prechecked": false
          }
        ]
      }
    ],
    "email_filter_by": "case_type",
    "filter": {
      "document_type": "cma_case"
    },
    "subscription_list_title_prefix": {
      "singular": "CMA cases with the following case type: ",
      "plural": "CMA cases with the following case types: ",
      "many": "Competition and Markets Authority (CMA) cases: "
    }
  }
}
